ValgrindCI/__init__.py
ValgrindCI/__main__.py
ValgrindCI/parse.py
ValgrindCI/py.typed
ValgrindCI/render.py
ValgrindCI/report.py
ValgrindCI/data/index.html
ValgrindCI/data/source_file.html
ValgrindCI/data/valgrind.css
ValgrindCI/data/valgrind.js
ValgrindCI-0.3.0.data/scripts/valgrind-ci
ValgrindCI-0.3.0.dist-info/LICENSE
ValgrindCI-0.3.0.dist-info/METADATA
ValgrindCI-0.3.0.dist-info/WHEEL
ValgrindCI-0.3.0.dist-info/top_level.txt
ValgrindCI-0.3.0.dist-info/RECORD
