Metadata-Version: 2.1
Name: ValgrindCI
Version: 0.3.0
Summary: Tools to integrate valgrind into your Continuous Integration workflow.
Home-page: https://github.com/bcoconni/ValgrindCI
Author: Bertrand Coconnier
Author-email: bcoconni@users.sourceforge.net
License: GNU General Public License v3.0
Keywords: valgrind valgrind-log-parsing html-report
Classifier: Development Status :: 4 - Beta
Classifier: Environment :: Console
Classifier: Intended Audience :: Developers
Classifier: License :: OSI Approved :: GNU General Public License v3 or later (GPLv3+)
Classifier: Operating System :: POSIX :: Linux
Classifier: Programming Language :: Python :: 3
Classifier: Topic :: Software Development :: Testing
License-File: LICENSE
Requires-Dist: defusedxml
Requires-Dist: jinja2
